Computer Organization/Lab0/Register_file.v
/**
 * SNU ECE Computer Organization
 *
 * Register_file.v
 */

module Register_file (
  input CLK,
  input RSTn,
  input WR,
  input [2:0] ADDR_A,
  input [2:0] ADDR_B,
  input [15:0] DATA_IN,

  output [15:0] DATA_A,
  output [15:0] DATA_B
);

////////////////////////////////////////////
reg [15:0] reg_array [7:0];

//reset operation and write operation are sequential
always@(!RSTn or WR) begin
	//TODO : reset
	if(!RSTn) begin
		reg_array[0] <= 16'h0000;
		reg_array[1] <= 16'h0000;
		reg_array[2] <= 16'h0000;
		reg_array[3] <= 16'h0000;
		reg_array[4] <= 16'h0000;
		reg_array[5] <= 16'h0000;
		reg_array[6] <= 16'h0000;
		reg_array[7] <= 16'h0000;
	end

	//TODO : write
	if(WR) begin
		reg_array[ADDR_A] <= DATA_IN;
		reg_array[ADDR_B] <= DATA_IN;
	end
end

//read operation is combinational
//TODO : read
assign DATA_A = reg_array[ADDR_A];
assign DATA_B = reg_array[ADDR_B];

////////////////////////////////////////////
endmodule

Computer Organization/Lab0/Register_file_tb.v
/**
 * SNU ECE Computer Organization
 *
 * Register_file_tb.v : test bench for the Register_file module
 */

`timescale 1ns / 100ps
module Register_file_tb;


wire [15:0] DATA_A, DATA_B;

reg [2:0] ADDR_A, ADDR_B;
reg [15:0] DATA_IN;
reg WR, CLK, RSTn;


/////////////////////////////////////
// TODO : change the "PORTNAME" and "MODULENAME" to appropriate names
/////////////////////////////////////
Register_file register 
( 
  .CLK(CLK),
  .RSTn(RSTn),
  .WR(WR),
  .ADDR_A(ADDR_A),
  .ADDR_B(ADDR_B),
  .DATA_IN(DATA_IN),
  .DATA_A(DATA_A),
  .DATA_B(DATA_B)
);
/////////////////////////////////////

integer i;

initial forever
  #5 CLK = ~CLK;

initial
begin

  CLK=1;

  RSTn = 1;
  #2  RSTn = 0;
  WR=0;
  #20   RSTn = 1;
  $display($time, " ********************** ");
  $display($time, " ** Start Simulation ** ");
  $display($time, " ********************** ");

  $display($time, " *** Register File **** ");
  $display($time, " ********************** ");
  for (i=0;i<8;i=i+1) begin
    $display($time, " Reg[%d]: %h (%b)", i, register.reg_array[i], register.reg_array[i]);
  end

  ////////// WRITE /////////

  $display($time, " ********************************* ");
  $display($time, " ** Write Data to Register File ** ");
  $display($time, " ********************************* ");
  ADDR_A = 3'b000;     // Select R0
  ADDR_B = 3'b001;     // Select R1

  #20   DATA_IN = 16'h1234;

  #20   WR = 1;     // Write to R1
  #10   WR = 0;

  $display($time, " [WRITE] Reg[1]: %h", register.reg_array[1]);
  if (register.reg_array[1] == 16'h1234) begin
    $display($time, " [WRITE] Correctly Write!");
  end
  else begin
    $display($time, " [WRITE] Incorrectly Written to Reg[1]..");
    $display($time, " [WRITE] True result is Reg[1]: 0x1234");
  end

  #20   ADDR_B = 3'b111;   // Select R7

  #20   DATA_IN = 16'h5678;

  #20   WR = 1;     // Write to R7
  #10   WR = 0;


  $display($time);
  $display($time, " [WRITE] Reg[7]: %h", register.reg_array[7]);
  if (register.reg_array[7] == 16'h5678) begin
    $display($time, " [WRITE] Correctly Write!");
  end
  else begin
    $display($time, " [WRITE] Incorrectly Written to Reg[7]..");
    $display($time, " [WRITE] True result is Reg[7]: 0x5678");
  end


  ///////////////////////////



  /////////// READ //////////

  $display($time, " ********************************** ");
  $display($time, " ** Read Data from Register File ** ");
  $display($time, " ********************************** ");
  #20   ADDR_A = 3'b100;   // Read R4
  ADDR_B = 4'b0101;   // Read R5
  #1
  $display($time, " [READ] Reg[4]: %h", DATA_A);
  if (DATA_A == 16'h0000) begin
    $display($time, " [READ] Correctly Read!");
  end
  else begin
    $display($time, "[READ] Incorrectly Read from Reg[4]..");
    $display($time, "[READ] True result is Reg[4]: 0x0000");
  end
  $display($time);
  $display($time, " [READ] Reg[5]: %h", DATA_B);
  if (DATA_B == 16'h0000) begin
    $display($time, " [READ] Correctly Read!");
  end
  else begin
    $display($time, " [READ] Incorrectly Read from Reg[5]..");
    $display($time, " [READ] True result is Reg[5]: 0x0000");
  end
  

  #20   ADDR_A = 3'b111;   // Read R7
  #1
  $display($time);
  $display($time, " [READ] Reg[7]: %h", DATA_A);
  if (DATA_A == 16'h5678) begin
    $display($time, " [READ] Correctly Read!");
  end
  else begin
    $display($time, " [READ] Incorrectly Read from Reg[7]..");
    $display($time, "[READ] True result is Reg[7]: 0x5678");
  end

  #20   ADDR_B = 3'b001;   // Read R1
  #1
  $display($time);
  $display($time, " [READ] Reg[1]: %h", DATA_B);
  if (DATA_B == 16'h1234) begin
    $display($time, " [READ] Correctly Read!");
  end
  else begin
    $display($time, " [READ] Incorrectly Read from Reg[1]..");
    $display($time, " [READ] True result is Reg[1]: 0x1234");
  end

  ////////////////////////////
  $display($time, " *********************** ");
  $display($time, " ** Finish Simulation ** ");
  $display($time, " *********************** ");
  $display($time, " *** Register File ***** ");
  $display($time, " *********************** ");
  for (i=0;i<8;i=i+1) begin
    $display($time, " Reg[%d]: %h (%b)", i, register.reg_array[i], register.reg_array[i]);
  end


  #20   RSTn = 0;
  #20   RSTn = 1;

  #40
  $finish;
end

// dump the state of the desgin
// VCD (Value Change Dump) is a standard dump format defined in Verilog
initial begin
  $dumpfile("Register_file.vcd");
  $dumpvars(0, Register_file_tb);
end

endmodule

Computer Organization/Lab0/Register_file.vcd
$date
	Tue Mar 28 00:05:55 2023
$end
$version
	Icarus Verilog
$end
$timescale
	100ps
$end
$scope module Register_file_tb $end
$var wire 16 ! DATA_B [15:0] $end
$var wire 16 " DATA_A [15:0] $end
$var reg 3 # ADDR_A [2:0] $end
$var reg 3 $ ADDR_B [2:0] $end
$var reg 1 % CLK $end
$var reg 16 & DATA_IN [15:0] $end
$var reg 1 ' RSTn $end
$var reg 1 ( WR $end
$var integer 32 ) i [31:0] $end
$scope module register $end
$var wire 3 * ADDR_A [2:0] $end
$var wire 3 + ADDR_B [2:0] $end
$var wire 1 % CLK $end
$var wire 16 , DATA_A [15:0] $end
$var wire 16 - DATA_B [15:0] $end
$var wire 16 . DATA_IN [15:0] $end
$var wire 1 ' RSTn $end
$var wire 1 ( WR $end
$upscope $end
$upscope $end
$enddefinitions $end
#0
$dumpvars
bx .
bx -
bx ,
bx +
bx *
bx )
x(
1'
bx &
1%
bx $
bx #
bx "
bx !
$end
#20
0(
0'
#50
0%
#100
1%
#150
0%
#200
1%
#220
b0 !
b0 -
b1 $
b1 +
b0 "
b0 ,
b0 #
b0 *
b1000 )
1'
#250
0%
#300
1%
#350
0%
#400
1%
#420
b1001000110100 &
b1001000110100 .
#450
0%
#500
1%
#550
0%
#600
1%
#620
b1001000110100 !
b1001000110100 -
b1001000110100 "
b1001000110100 ,
1(
#650
0%
#700
1%
#720
0(
#750
0%
#800
1%
#850
0%
#900
1%
#920
b0 !
b0 -
b111 $
b111 +
#950
0%
#1000
1%
#1050
0%
#1100
1%
#1120
b101011001111000 &
b101011001111000 .
#1150
0%
#1200
1%
#1250
0%
#1300
1%
#1320
b101011001111000 !
b101011001111000 -
b101011001111000 "
b101011001111000 ,
1(
#1350
0%
#1400
1%
#1420
0(
#1450
0%
#1500
1%
#1550
0%
#1600
1%
#1620
b0 !
b0 -
b101 $
b101 +
b0 "
b0 ,
b100 #
b100 *
#1650
0%
#1700
1%
#1750
0%
#1800
1%
#1830
b101011001111000 "
b101011001111000 ,
b111 #
b111 *
#1850
0%
#1900
1%
#1950
0%
#2000
1%
#2040
b1001000110100 !
b1001000110100 -
b1 $
b1 +
#2050
b1000 )
0%
#2100
1%
#2150
0%
#2200
1%
#2250
b0 "
b0 ,
b0 !
b0 -
0%
0'
#2300
1%
#2350
0%
#2400
1%
#2450
0%
1'
